{"cameraMode":{"drawMode":0,"name":"Shaded","section":"Shading Mode"},"sceneLighting":true,"audioPlay":false,"sceneViewState":{"showFog":true,"showMaterialUpdate":false,"showSkybox":true,"showFlares":true,"showImageEffects":true,"showParticleSystems":true},"in2DMode":false,"pivot":{"x":-11.805024147033692,"y":-12.122668266296387,"z":2.4617655277252199},"rotation":{"x":0.31508341431617739,"y":-0.5777124166488648,"z":0.2571306824684143,"w":0.7077589631080627},"size":13.308538436889649,"orthographic":false}